<xml xmlns="http://www.w3.org/1999/xhtml">
  <block type="controls_whileUntil" id="766" inline="false" x="-48" y="-54">
    <field name="MODE">UNTIL</field>
    <value name="NUMBER">
      <block type="sensor_button" id="725">
        <field name="OBJECT">UP</field>
      </block>
    </value>
    <statement name="DO">
      <block type="led_select" id="797" inline="true">
        <field name="ACTION">FLASH</field>
        <value name="LED">
          <block type="math_number" id="823">
            <field name="NUM">100</field>
          </block>
        </value>
        <next>
          <block type="led_select" id="810" inline="true">
            <field name="ACTION">FLASH</field>
            <value name="LED">
              <block type="math_number" id="824">
                <field name="NUM">100</field>
              </block>
            </value>
            <next>
              <block type="robot_delay" id="812" inline="true">
                <value name="DELAY">
                  <block type="math_number" id="830">
                    <field name="NUM">5000000</field>
                  </block>
                </value>
              </block>
            </next>
          </block>
        </next>
      </block>
    </statement>
  </block>
  <block type="math_number" id="831" x="357" y="634">
    <field name="NUM">0</field>
  </block>
  <block type="math_number" id="832" x="377" y="674">
    <field name="NUM">0</field>
  </block>
  <block type="math_number" id="833" x="397" y="714">
    <field name="NUM">0</field>
  </block>
</xml>